README.rst
setup.cfg
setup.py
apn/__init__.py
apn/apn.py
apn.egg-info/PKG-INFO
apn.egg-info/SOURCES.txt
apn.egg-info/dependency_links.txt
apn.egg-info/entry_points.txt
apn.egg-info/not-zip-safe
apn.egg-info/requires.txt
apn.egg-info/top_level.txt
apn/cli/__init__.py
apn/cli/apn.py
apn/data/abbrev.pkl
apn/data/apn.pkl
apn/data/state.pkl