Metadata-Version: 1.1
Name: apn
Version: 2.0.7
Summary: Accessor Parcel Number format lookup
Home-page: https://github.com/dogpackdesign/apn-formats
Author: Eric Proulx
Author-email: eric@ericproulx.com
License: MIT
Keywords: apn real estate format
Platform: any
Classifier: Development Status :: 3 - Alpha
Classifier: Programming Language :: Python :: 2.7
Classifier: Programming Language :: Python :: 3.3
Classifier: Programming Language :: Python :: 3.4
Classifier: Programming Language :: Python :: 3.5
Classifier: Programming Language :: Python :: 3.6
